[
  {
    "id": 1,
    "file-name": "bitterling",
    "name": {},
    "availability": {
      "month-northern": "11-3",
      "month-southern": "5-9",
      "time": "",
      "isAllDay": true,
      "isAllYear": false,
      "location": "River",
      "rarity": "Common",
      "month-array-northern": [11, 12, 1, 2, 3],
      "month-array-southern": [],
      "time-array": []
    },
    "shadow": "Smallest (1)",
    "price": 900,
    "price-cj": 1350,
    "catch-phrase": "I caught a bitterling! It's mad at me, but only a little.",
    "museum-phrase": "Bitterlings hide their eggs inside large bivalves—like clams—where the young can stay safe until grown. The bitterling isn't being sneaky. No, their young help keep the bivalve healthy by eating invading parasites! It's a wonderful bit of evolutionary deal making, don't you think? Each one keeping the other safe... Though eating parasites does not sound like a happy childhood... Is that why the fish is so bitter?",
    "image_uri": "https://acnhapi.com/v1/images/fish/1",
    "icon_uri": "https://acnhapi.com/v1/icons/fish/1"
  },
  {
    "id": 2,
    "file-name": "pale_chub",
    "name": {},
    "availability": {
      "month-northern": "",
      "month-southern": "",
      "time": "9am - 4pm",
      "isAllDay": false,
      "isAllYear": true,
      "location": "River",
      "rarity": "Common",
      "month-array-northern": [1, 2, 3, 4, 5, 6, 7, 8, 9, 10, 11, 12],
      "month-array-southern": [],
      "time-array": []
    },
    "shadow": "Smallest (1)",
    "price": 200,
    "price-cj": 300,
    "catch-phrase": "I caught a pale chub! That name seems a bit judgy...",
    "museum-phrase": "The pale chub is a river fish with simple back-and-silver coloring. Interestingly, the males' coloring becomes most vibrant when he's trying to attract a mate! Though normally plain, these fellows really know how to look stylish when they want to. Perhaps I could learn a thing or two from the pale chub...",
    "image_uri": "https://acnhapi.com/v1/images/fish/2",
    "icon_uri": "https://acnhapi.com/v1/icons/fish/2"
  },
  {
    "id": 3,
    "file-name": "crucian_carp",
    "name": {},
    "availability": {
      "month-northern": "",
      "month-southern": "",
      "time": "",
      "isAllDay": true,
      "isAllYear": true,
      "location": "River",
      "rarity": "Common",
      "month-array-northern": [1, 2, 3, 4, 5, 6, 7, 8, 9, 10, 11, 12],
      "month-array-southern": [],
      "time-array": []
    },
    "shadow": "Small (2)",
    "price": 160,
    "price-cj": 240,
    "catch-phrase": "I caught a crucian carp! My skills are sharp!",
    "museum-phrase": "I wonder... Do you know how to tell the difference between a crucian carp and a standard-issue carp? It's quite easy to tell the two apart... One must simply locate the barbels. Or, rather, the lack of them! And just what is a barbel, you ask? Well, a barbel looks a little something like a mustache. A run-of-the-mill carp will sport this unsightly \"facial hair,\" while a crucian carp is considerably better groomed! I tried to grow a mustache when I was younger. It never did fill in quite right... All for the best in the end, as mustaches go so much better with noses than with beaks!",
    "image_uri": "https://acnhapi.com/v1/images/fish/3",
    "icon_uri": "https://acnhapi.com/v1/icons/fish/3"
  },
  {
    "id": 4,
    "file-name": "dace",
    "name": {},
    "availability": {
      "month-northern": "",
      "month-southern": "",
      "time": "4pm - 9am",
      "isAllDay": false,
      "isAllYear": true,
      "location": "River",
      "rarity": "Common",
      "month-array-northern": [1, 2, 3, 4, 5, 6, 7, 8, 9, 10, 11, 12],
      "month-array-southern": [],
      "time-array": []
    },
    "shadow": "Medium (3)",
    "price": 240,
    "price-cj": 360,
    "catch-phrase": "I caught a dace! Hope I have some space!",
    "museum-phrase": "Dace are shiny little fish that enjoy freshwater streams with gravelly bottoms and plenty of sunlight. What a fishy paradise...until the larger fish move in and begin eating the dace! Sadly, the shiny dace are easy for other fish to spot, which makes them a popular snack. However, this particular specimen here has no need to worry. There's a strict \"No Eating Your Neighbor\" policy at this institution.",
    "image_uri": "https://acnhapi.com/v1/images/fish/4",
    "icon_uri": "https://acnhapi.com/v1/icons/fish/4"
  },
  {
    "id": 5,
    "file-name": "carp",
    "name": {},
    "availability": {
      "month-northern": "",
      "month-southern": "",
      "time": "",
      "isAllDay": true,
      "isAllYear": true,
      "location": "Pond",
      "rarity": "Common",
      "month-array-northern": [1, 2, 3, 4, 5, 6, 7, 8, 9, 10, 11, 12],
      "month-array-southern": [],
      "time-array": []
    },
    "shadow": "Medium (4)",
    "price": 300,
    "price-cj": 450,
    "catch-phrase": "I caught a carp! If I catch another they can carpool!",
    "museum-phrase": "Oh, the carp... have you ever seen their teeth? For your sake, I hope you have not! Carp have teeth in their throat strong enough to crunch on hard things like shells and fingers! A good rule of thumb when dealing with other species is to keep your fingers out of their mouths. Although, having neither thumbs nor fingers, I am quite safe from this little fellow!",
    "image_uri": "https://acnhapi.com/v1/images/fish/5",
    "icon_uri": "https://acnhapi.com/v1/icons/fish/5"
  },
  {
    "id": 6,
    "file-name": "koi",
    "name": {},
    "availability": {
      "month-northern": "",
      "month-southern": "",
      "time": "4pm - 9am",
      "isAllDay": false,
      "isAllYear": true,
      "location": "Pond",
      "rarity": "Uncommon",
      "month-array-northern": [1, 2, 3, 4, 5, 6, 7, 8, 9, 10, 11, 12],
      "month-array-southern": [],
      "time-array": []
    },
    "shadow": "Medium (4)",
    "price": 4000,
    "price-cj": 6000,
    "catch-phrase": "I caught a koi! I don't know why it's so shy... or such a bad speller...",
    "museum-phrase": "Koi are a variety of carp bred for their color mutations...starting more than a thousand years ago! Well, one glance at their impressive coloring tells you that the centuries of effort were worth it. And even today people still selectively breed koi in search of new color combinations! One marvels at the thought of what the koi may look like in another thousand years.",
    "image_uri": "https://acnhapi.com/v1/images/fish/6",
    "icon_uri": "https://acnhapi.com/v1/icons/fish/6"
  },
  {
    "id": 7,
    "file-name": "goldfish",
    "name": {},
    "availability": {
      "month-northern": "",
      "month-southern": "",
      "time": "",
      "isAllDay": true,
      "isAllYear": true,
      "location": "Pond",
      "rarity": "Common",
      "month-array-northern": [1, 2, 3, 4, 5, 6, 7, 8, 9, 10, 11, 12],
      "month-array-southern": [],
      "time-array": []
    },
    "shadow": "Smallest (1)",
    "price": 1300,
    "price-cj": 1950,
    "catch-phrase": "I caught a goldfish! It's worth its weight in fish!",
    "museum-phrase": "Goldfish are so cute and delicate... but do you know how big they can get? Why, they can grow up to... a foot in length! Well, sometimes. The size of the tank they're kept in tends to restrict their growth. And just how big will this goldfish get in our large museum tank? I look forward to finding out!",
    "image_uri": "https://acnhapi.com/v1/images/fish/7",
    "icon_uri": "https://acnhapi.com/v1/icons/fish/7"
  },
  {
    "id": 8,
    "file-name": "pop-eyed_goldfish",
    "name": {},
    "availability": {
      "month-northern": "",
      "month-southern": "",
      "time": "9am - 4pm",
      "isAllDay": false,
      "isAllYear": true,
      "location": "Pond",
      "rarity": "Common",
      "month-array-northern": [1, 2, 3, 4, 5, 6, 7, 8, 9, 10, 11, 12],
      "month-array-southern": [],
      "time-array": []
    },
    "shadow": "Smallest (1)",
    "price": 1300,
    "price-cj": 1950,
    "catch-phrase": "I got a pop-eyed goldfish! It looks so...surprised!",
    "museum-phrase": "Pop-eyed goldfish have, as the name suggests, huge round eyes. But as babies they look like other goldfish! As they grow, their eyes begin to pop out and they gain their, hoo, distinct appearance... Imagine the poor fish fancier who unknowingly bought one! Their eyes might well pop out just as far!",
    "image_uri": "https://acnhapi.com/v1/images/fish/8",
    "icon_uri": "https://acnhapi.com/v1/icons/fish/8"
  },
  {
    "id": 9,
    "file-name": "ranchu_goldfish",
    "name": {},
    "availability": {
      "month-northern": "",
      "month-southern": "",
      "time": "9am - 4pm",
      "isAllDay": false,
      "isAllYear": true,
      "location": "Pond",
      "rarity": "Uncommon",
      "month-array-northern": [1, 2, 3, 4, 5, 6, 7, 8, 9, 10, 11, 12],
      "month-array-southern": [],
      "time-array": []
    },
    "shadow": "Small (2)",
    "price": 4500,
    "price-cj": 6750,
    "catch-phrase": "I caught a ranchu goldfish! But I prefer balsamicu goldfish!",
    "museum-phrase": "The ranchu goldfish is a charming relative of the goldfish with a bumpy head and stout, round body. They have ordinary heads when born, but develop impressive rectangular heads after about three years. Supposedly their head shape changes depending on factors like the size of their tank... So ranchu goldfish enthusiasts aim to raise perfectly shaped specimens and work hard to achieve this. Of course, no one asks the ranchu goldfish themselves what shape they want their heads to be...",
    "image_uri": "https://acnhapi.com/v1/images/fish/9",
    "icon_uri": "https://acnhapi.com/v1/icons/fish/9"
  },
  {
    "id": 10,
    "file-name": "killifish",
    "name": {},
    "availability": {
      "month-northern": "4-8",
      "month-southern": "10-2",
      "time": "",
      "isAllDay": true,
      "isAllYear": false,
      "location": "Pond",
      "rarity": "Common",
      "month-array-northern": [4, 5, 6, 7, 8],
      "month-array-southern": [],
      "time-array": []
    },
    "shadow": "Smallest (1)",
    "price": 300,
    "price-cj": 450,
    "catch-phrase": "I caught a killifish! The streams are safe again.",
    "museum-phrase": "Ah, the magnificent killifish! Did you know there are over 1,000 different species? My own favorite killifish species are the mangrove, which can live on land for weeks, breathing air! And the mummichog, the first fish ever brought to space. I wonder if the killifish you've brought me is related to either those intrepid explorers?",
    "image_uri": "https://acnhapi.com/v1/images/fish/10",
    "icon_uri": "https://acnhapi.com/v1/icons/fish/10"
  }
]
